gent/__init__.py
gent/internal/__init__.py
gent/internal/box.py
gent/internal/canvas.py
gent/internal/event.py
gent/internal/gameObject.py
gent/internal/selection.py
gent/internal/timing.py
gent/math/__init__.py
gent/math/sampling.py
gent/objects/__init__.py
gent/objects/inputBox.py
gent/objects/selector.py
gent/objects/textBox.py
gent/objects/textLine.py
gent/utilities/__init__.py
gent/utilities/color.py
gent/utilities/text/__init__.py
gent/utilities/text/lineSplitter.py
gent/window/__init__.py
gent/window/getch.py
gent/window/window.py
gent-0.0.1a1.dist-info/LICENSE.txt
gent-0.0.1a1.dist-info/METADATA
gent-0.0.1a1.dist-info/WHEEL
gent-0.0.1a1.dist-info/top_level.txt
gent-0.0.1a1.dist-info/RECORD
