Metadata-Version: 2.1
Name: gent
Version: 0.0.1a1
Summary: gent (Game ENgine for Terminals), is a library to allow game like interactions in user terminals
Home-page: https://github.com/flywinged/gent
Author: Clayton Brown
Author-email: clayton.john.brown@gmail.com
License: MIT
Keywords: Terminal,Graphics,Game,Engine
Platform: UNKNOWN
Classifier: Development Status :: 3 - Alpha
Classifier: Intended Audience :: Developers
Classifier: Topic :: Software Development :: Build Tools
Classifier: License :: OSI Approved :: MIT License
Classifier: Programming Language :: Python :: 3.6
Requires-Dist: numpy
Requires-Dist: colorama
Requires-Dist: sty
Requires-Dist: dataclasses
